curtis/__init__.py
curtis/engine.py
curtis/exceptions.py
curtis/facts.py
curtis/data/validation_sample.csv
curtis/model/curtis.sav
curtis/utils/__init__.py
curtis/utils/encoding.py
curtis/utils/validation.py
test/__init__.py
test/test_encoding.py
test/test_engine.py
test/test_exceptions.py
test/test_fact.py
test/test_model.py
test/test_validation.py
curtis_engine-1.0.0.dist-info/LICENSE.md
curtis_engine-1.0.0.dist-info/METADATA
curtis_engine-1.0.0.dist-info/WHEEL
curtis_engine-1.0.0.dist-info/top_level.txt
curtis_engine-1.0.0.dist-info/RECORD
