Metadata-Version: 2.1
Name: curtis-engine
Version: 1.0.0
Summary: The cardiovascular unified real-time intelligent system
Home-page: UNKNOWN
Author: Gabriel Moreno
Author-email: gantoreno@gmail.com
License: UNKNOWN
Platform: UNKNOWN
Classifier: Programming Language :: Python :: 3
Classifier: License :: OSI Approved :: MIT License
Classifier: Operating System :: OS Independent
Requires-Python: >=3.5
Requires-Dist: scikit-learn (==0.23.2)
